Workbook

Sheet Assumptions
A1: DDMF RKAP 2026 projects: employment model — assumptions (RESTRICTED: uses DDMF RKAP 2026 data)
A2: Blue = input you can change; black = formula; green = link to another sheet. Yellow cells are key assumptions.
A4: Build phase: job-years per Rp 1 trillion of investment (Type I = direct + indirect), 2025 prices
A5: Category | B5: Code | C5: ERIA PSN job-years per Rp 1 bn (2016–22 prices) | D5: Price rebase factor | E5: Uplift factor | F5: Type-I job-years per Rp 1 T | G5: Direct share of Type I | H5: Source / note
A6: Civil works (sea wall, water, urban, parks) | B6: CIV | C6: 5.7 | D6: =$C$17 -> 1.298722 | E6: 1 | F6: =C6*1000/D6*E6 -> 4388.9299 | G6: 0.55 | H6: ERIA (2023) Table 5.5, roads & bridges
A7: Buildings (housing, schools, campus) | B7: BLD | C7: 5.7 | D7: =$C$17 -> 1.298722 | E7: 1.15 | F7: =C7*1000/D7*E7 -> 5047.2694 | G7: 0.58 | H7: Roads coefficient +15% for more labour-intensive building work (author's assumption)
A8: Industry / manufacturing plants | B8: IND | C8: 5.54 | D8: =$C$17 -> 1.298722 | E8: 1 | F8: =C8*1000/D8*E8 -> 4265.7319 | G8: 0.45 | H8: ERIA (2023) Table 5.5, industrial zones
A9: Power and waste-to-energy | B9: PWR | C9: 5.54 | D9: =$C$17 -> 1.298722 | E9: 1 | F9: =C9*1000/D9*E9 -> 4265.7319 | G9: 0.45 | H9: ERIA (2023) Table 5.5, electricity
A10: Solar PV (modules largely imported) | B10: PV | C10: 5.54 | D10: =$C$17 -> 1.298722 | E10: 0.8 | F10: =C10*1000/D10*E10 -> 3412.5855 | G10: 0.45 | H10: Electricity coefficient −20% for imported modules (author's assumption)
A11: Smelters, refining, petrochemicals | B11: SML | C11: 3.71 | D11: =$C$17 -> 1.298722 | E11: 1 | F11: =C11*1000/D11*E11 -> 2856.6544 | G11: 0.4 | H11: ERIA (2023) Table 5.5, smelters
A12: Technology and digital | B12: TEC | C12: 4.3 | D12: =$C$17 -> 1.298722 | E12: 1 | F12: =C12*1000/D12*E12 -> 3310.9471 | G12: 0.4 | H12: ERIA (2023) Table 5.5, technology
A14: Price rebase
A15: GDP per worker 2019 (Rp million) | C15: 125.2 | H15: BPS: nominal GDP 2019 Rp 15,833.9 T ÷ 126.51 m employed (Aug 2019)
A16: GDP per worker 2025 (Rp million) | C16: 162.6 | H16: BPS: nominal GDP 2025 Rp 23,821.1 T ÷ 146.54 m employed (Aug 2025)
A17: Rebase factor (2025 ÷ 2019) | C17: =C16/C15 -> 1.298722
A19: Multipliers
A20: Induced jobs as share of Type-I jobs | C20: 0.35 | H20: Household spending of wages; Type II/Type I ratios of 1.3–1.5 are typical (author's assumption)
A21: Indirect operating jobs per direct operating job | C21: 0.8 | H21: Supply chains of operating plants (author's assumption)
A23: Labour market (BPS Sakernas)
A24: Labour force, Feb 2026 (million) | C24: 154.91 | H24: Employed 147.67 m + unemployed 7.24 m (BPS, Feb 2026)
A25: Unemployed, Feb 2026 (million) | C25: 7.24
A26: Open unemployment rate, Feb 2026 | C26: =C25/C24 -> 0.046736815 | H26: BPS reports 4.68%
A27: Labour-force growth a year | C27: 0.0122 | H27: Feb 2025 → Feb 2026 (BPS)
A28: Share of extra jobs that reduce open unemployment | C28: 0.4 | H28: Central 40% (range 25–55%): the rest go to new entrants, returning workers, the 10.7 m underemployed and job-switchers (author's assumption)

Sheet Projects
A1: Project | B1: Cluster | C1: Investment (Rp T) | D1: Start | E1: End | F1: Category | G1: Domestic-content adj. | H1: Type-I job-years per Rp 1 T | I1: Direct share | J1: Direct job-years | K1: Indirect job-years | L1: Induced job-years | M1: Total job-years (build) | N1: Jobs a year during build | O1: Permanent direct jobs per Rp 1 T | P1: Permanent direct jobs | Q1: Permanent indirect + induced jobs | R1: Permanent jobs (total) | S1: Labour note
A2: CDME (coal to DME) | B2: NR | C2: 46.28 | D2: 2027 | E2: 2030 | F2: SML | G2: 1 | H2: =INDEX(Assumptions!$F$6:$F$12,MATCH(F2,Assumptions!$B$6:$B$12,0))*G2 -> 2856.6544 | I2: =INDEX(Assumptions!$G$6:$G$12,MATCH(F2,Assumptions!$B$6:$B$12,0)) -> 0.4 | J2: =C2*H2*I2 -> 52882.386 | K2: =C2*H2*(1-I2) -> 79323.578 | L2: =(J2+K2)*Assumptions!$C$20 -> 46272.087 | M2: =J2+K2+L2 -> 178478.05 | N2: =M2/(E2-D2+1) -> 44619.513 | O2: 60 | P2: =C2*O2 -> 2776.8 | Q2: =P2*Assumptions!$C$21+P2*(1+Assumptions!$C$21)*Assumptions!$C$20 -> 3970.824 | R2: =P2+Q2 -> 6747.624 | S2: Capital-intensive gasification plant; few operators
A3: PLTS 100 GW (solar) | B3: NR | C3: 231.4 | D3: 2027 | E3: 2030 | F3: PV | G3: 1 | H3: =INDEX(Assumptions!$F$6:$F$12,MATCH(F3,Assumptions!$B$6:$B$12,0))*G3 -> 3412.5855 | I3: =INDEX(Assumptions!$G$6:$G$12,MATCH(F3,Assumptions!$B$6:$B$12,0)) -> 0.45 | J3: =C3*H3*I3 -> 355352.53 | K3: =C3*H3*(1-I3) -> 434319.75 | L3: =(J3+K3)*Assumptions!$C$20 -> 276385.3 | M3: =J3+K3+L3 -> 1066057.6 | N3: =M3/(E3-D3+1) -> 266514.39 | O3: 100 | P3: =C3*O3 -> 23140 | Q3: =P3*Assumptions!$C$21+P3*(1+Assumptions!$C$21)*Assumptions!$C$20 -> 33090.2 | R3: =P3+Q3 -> 56230.2 | S3: Installation labour is significant; modules largely imported; O&M light
A4: Refinery | B4: NR | C4: 40.94 | D4: 2027 | E4: 2032 | F4: SML | G4: 1 | H4: =INDEX(Assumptions!$F$6:$F$12,MATCH(F4,Assumptions!$B$6:$B$12,0))*G4 -> 2856.6544 | I4: =INDEX(Assumptions!$G$6:$G$12,MATCH(F4,Assumptions!$B$6:$B$12,0)) -> 0.4 | J4: =C4*H4*I4 -> 46780.572 | K4: =C4*H4*(1-I4) -> 70170.858 | L4: =(J4+K4)*Assumptions!$C$20 -> 40933 | M4: =J4+K4+L4 -> 157884.43 | N4: =M4/(E4-D4+1) -> 26314.072 | O4: 40 | P4: =C4*O4 -> 1637.6 | Q4: =P4*Assumptions!$C$21+P4*(1+Assumptions!$C$21)*Assumptions!$C$20 -> 2341.768 | R4: =P4+Q4 -> 3979.368 | S4: Very capital-intensive; skilled operators
A5: CPE (assumed petrochemical) | B5: NR | C5: 71.2 | D5: 2028 | E5: 2031 | F5: SML | G5: 1 | H5: =INDEX(Assumptions!$F$6:$F$12,MATCH(F5,Assumptions!$B$6:$B$12,0))*G5 -> 2856.6544 | I5: =INDEX(Assumptions!$G$6:$G$12,MATCH(F5,Assumptions!$B$6:$B$12,0)) -> 0.4 | J5: =C5*H5*I5 -> 81357.516 | K5: =C5*H5*(1-I5) -> 122036.27 | L5: =(J5+K5)*Assumptions!$C$20 -> 71187.827 | M5: =J5+K5+L5 -> 274581.62 | N5: =M5/(E5-D5+1) -> 68645.404 | O5: 50 | P5: =C5*O5 -> 3560 | Q5: =P5*Assumptions!$C$21+P5*(1+Assumptions!$C$21)*Assumptions!$C$20 -> 5090.8 | R5: =P5+Q5 -> 8650.8 | S5: Petrochemical complex; capital-intensive
A6: Biodiesel | B6: NR | C6: 75.388 | D6: 2028 | E6: 2031 | F6: IND | G6: 1 | H6: =INDEX(Assumptions!$F$6:$F$12,MATCH(F6,Assumptions!$B$6:$B$12,0))*G6 -> 4265.7319 | I6: =INDEX(Assumptions!$G$6:$G$12,MATCH(F6,Assumptions!$B$6:$B$12,0)) -> 0.45 | J6: =C6*H6*I6 -> 144713.25 | K6: =C6*H6*(1-I6) -> 176871.75 | L6: =(J6+K6)*Assumptions!$C$20 -> 112554.75 | M6: =J6+K6+L6 -> 434139.74 | N6: =M6/(E6-D6+1) -> 108534.94 | O6: 120 | P6: =C6*O6 -> 9046.56 | Q6: =P6*Assumptions!$C$21+P6*(1+Assumptions!$C$21)*Assumptions!$C$20 -> 12936.581 | R6: =P6+Q6 -> 21983.141 | S6: Plant jobs plus feedstock logistics; plantation jobs mostly existing
A7: Legacy waste – landfill mining | B7: NR | C7: 6 | D7: 2028 | E7: 2031 | F7: PWR | G7: 1 | H7: =INDEX(Assumptions!$F$6:$F$12,MATCH(F7,Assumptions!$B$6:$B$12,0))*G7 -> 4265.7319 | I7: =INDEX(Assumptions!$G$6:$G$12,MATCH(F7,Assumptions!$B$6:$B$12,0)) -> 0.45 | J7: =C7*H7*I7 -> 11517.476 | K7: =C7*H7*(1-I7) -> 14076.915 | L7: =(J7+K7)*Assumptions!$C$20 -> 8958.0369 | M7: =J7+K7+L7 -> 34552.428 | N7: =M7/(E7-D7+1) -> 8638.107 | O7: 400 | P7: =C7*O7 -> 2400 | Q7: =P7*Assumptions!$C$21+P7*(1+Assumptions!$C$21)*Assumptions!$C$20 -> 3432 | R7: =P7+Q7 -> 5832 | S7: Labour-intensive sorting and excavation
A8: Legacy waste – RDF | B8: NR | C8: 6 | D8: 2028 | E8: 2031 | F8: PWR | G8: 1 | H8: =INDEX(Assumptions!$F$6:$F$12,MATCH(F8,Assumptions!$B$6:$B$12,0))*G8 -> 4265.7319 | I8: =INDEX(Assumptions!$G$6:$G$12,MATCH(F8,Assumptions!$B$6:$B$12,0)) -> 0.45 | J8: =C8*H8*I8 -> 11517.476 | K8: =C8*H8*(1-I8) -> 14076.915 | L8: =(J8+K8)*Assumptions!$C$20 -> 8958.0369 | M8: =J8+K8+L8 -> 34552.428 | N8: =M8/(E8-D8+1) -> 8638.107 | O8: 300 | P8: =C8*O8 -> 1800 | Q8: =P8*Assumptions!$C$21+P8*(1+Assumptions!$C$21)*Assumptions!$C$20 -> 2574 | R8: =P8+Q8 -> 4374 | S8: Sorting and processing lines
A9: Fishing-village food security | B9: NR | C9: 83.765 | D9: 2028 | E9: 2031 | F9: CIV | G9: 1 | H9: =INDEX(Assumptions!$F$6:$F$12,MATCH(F9,Assumptions!$B$6:$B$12,0))*G9 -> 4388.9299 | I9: =INDEX(Assumptions!$G$6:$G$12,MATCH(F9,Assumptions!$B$6:$B$12,0)) -> 0.55 | J9: =C9*H9*I9 -> 202201.29 | K9: =C9*H9*(1-I9) -> 165437.42 | L9: =(J9+K9)*Assumptions!$C$20 -> 128673.55 | M9: =J9+K9+L9 -> 496312.26 | N9: =M9/(E9-D9+1) -> 124078.07 | O9: 1000 | P9: =C9*O9 -> 83765 | Q9: =P9*Assumptions!$C$21+P9*(1+Assumptions!$C$21)*Assumptions!$C$20 -> 119783.95 | R9: =P9+Q9 -> 203548.95 | S9: Cold chains, boats, processing: many small jobs, part upgrading existing work
A10: Silica | B10: NR | C10: 8.9 | D10: 2028 | E10: 2031 | F10: SML | G10: 1 | H10: =INDEX(Assumptions!$F$6:$F$12,MATCH(F10,Assumptions!$B$6:$B$12,0))*G10 -> 2856.6544 | I10: =INDEX(Assumptions!$G$6:$G$12,MATCH(F10,Assumptions!$B$6:$B$12,0)) -> 0.4 | J10: =C10*H10*I10 -> 10169.69 | K10: =C10*H10*(1-I10) -> 15254.534 | L10: =(J10+K10)*Assumptions!$C$20 -> 8898.4784 | M10: =J10+K10+L10 -> 34322.702 | N10: =M10/(E10-D10+1) -> 8580.6756 | O10: 200 | P10: =C10*O10 -> 1780 | Q10: =P10*Assumptions!$C$21+P10*(1+Assumptions!$C$21)*Assumptions!$C$20 -> 2545.4 | R10: =P10+Q10 -> 4325.4 | S10: Mining and processing of silica sand
A11: Copper | B11: NR | C11: 2 | D11: 2028 | E11: 2031 | F11: SML | G11: 1 | H11: =INDEX(Assumptions!$F$6:$F$12,MATCH(F11,Assumptions!$B$6:$B$12,0))*G11 -> 2856.6544 | I11: =INDEX(Assumptions!$G$6:$G$12,MATCH(F11,Assumptions!$B$6:$B$12,0)) -> 0.4 | J11: =C11*H11*I11 -> 2285.3235 | K11: =C11*H11*(1-I11) -> 3427.9852 | L11: =(J11+K11)*Assumptions!$C$20 -> 1999.6581 | M11: =J11+K11+L11 -> 7712.9668 | N11: =M11/(E11-D11+1) -> 1928.2417 | O11: 150 | P11: =C11*O11 -> 300 | Q11: =P11*Assumptions!$C$21+P11*(1+Assumptions!$C$21)*Assumptions!$C$20 -> 429 | R11: =P11+Q11 -> 729 | S11: Processing; Danantara/IMIP benchmark 130–170 per Rp 1 T
A12: Project Anoa (rare earths) | B12: NR | C12: 0.38 | D12: 2027 | E12: 2031 | F12: SML | G12: 1 | H12: =INDEX(Assumptions!$F$6:$F$12,MATCH(F12,Assumptions!$B$6:$B$12,0))*G12 -> 2856.6544 | I12: =INDEX(Assumptions!$G$6:$G$12,MATCH(F12,Assumptions!$B$6:$B$12,0)) -> 0.4 | J12: =C12*H12*I12 -> 434.21146 | K12: =C12*H12*(1-I12) -> 651.3172 | L12: =(J12+K12)*Assumptions!$C$20 -> 379.93503 | M12: =J12+K12+L12 -> 1465.4637 | N12: =M12/(E12-D12+1) -> 293.09274 | O12: 150 | P12: =C12*O12 -> 57 | Q12: =P12*Assumptions!$C$21+P12*(1+Assumptions!$C$21)*Assumptions!$C$20 -> 81.51 | R12: =P12+Q12 -> 138.51 | S12: Small processing pilot
A13: Project Tarsius Ph.1 (rare earths) | B13: NR | C13: 2.3 | D13: 2029 | E13: 2032 | F13: SML | G13: 1 | H13: =INDEX(Assumptions!$F$6:$F$12,MATCH(F13,Assumptions!$B$6:$B$12,0))*G13 -> 2856.6544 | I13: =INDEX(Assumptions!$G$6:$G$12,MATCH(F13,Assumptions!$B$6:$B$12,0)) -> 0.4 | J13: =C13*H13*I13 -> 2628.122 | K13: =C13*H13*(1-I13) -> 3942.183 | L13: =(J13+K13)*Assumptions!$C$20 -> 2299.6068 | M13: =J13+K13+L13 -> 8869.9118 | N13: =M13/(E13-D13+1) -> 2217.478 | O13: 150 | P13: =C13*O13 -> 345 | Q13: =P13*Assumptions!$C$21+P13*(1+Assumptions!$C$21)*Assumptions!$C$20 -> 493.35 | R13: =P13+Q13 -> 838.35 | S13: Processing; benchmark 130–170 per Rp 1 T
... A36: E-commerce | B36: OTH | C36: 1 | D36: 2028 | E36: 2031 | F36: TEC | G36: 1 | H36: =INDEX(Assumptions!$F$6:$F$12,MATCH(F36,Assumptions!$B$6:$B$12,0))*G36 -> 3310.9471 | I36: =INDEX(Assumptions!$G$6:$G$12,MATCH(F36,Assumptions!$B$6:$B$12,0)) -> 0.4 | J36: =C36*H36*I36 -> 1324.3788 | K36: =C36*H36*(1-I36) -> 1986.5683 | L36: =(J36+K36)*Assumptions!$C$20 -> 1158.8315 | M36: =J36+K36+L36 -> 4469.7786 | N36: =M36/(E36-D36+1) -> 1117.4446 | O36: 200 | P36: =C36*O36 -> 200 | Q36: =P36*Assumptions!$C$21+P36*(1+Assumptions!$C$21)*Assumptions!$C$20 -> 286 | R36: =P36+Q36 -> 486 | S36: Platform and logistics staff
A37: Total (35 costed projects) | C37: =SUM(C2:C36) -> 2091.475 | J37: =SUM(J2:J36) -> 4382421.1 | K37: =SUM(K2:K36) -> 4070900.7 | L37: =SUM(L2:L36) -> 2958662.6 | M37: =SUM(M2:M36) -> 11411984 | P37: =SUM(P2:P36) -> 401727.17 | Q37: =SUM(Q2:Q36) -> 574469.85 | R37: =SUM(R2:R36) -> 976197.02
A39: Five further projects (IMX, ERP Merah Putih, electric stoves, high-speed rail, Trans-Sumatra toll road) have no RKAP cost and are excluded.
A40: Permanent operating jobs per Rp 1 T: benchmarks — IMIP Morowali 89,849 workers on Rp 697 T (≈129); Danantara 26 downstream projects 37,833 jobs on Rp 225 T (≈168); others are author's assumptions noted per row.

Sheet By year
A1: Year | B1: Direct (build) | C1: Indirect (build) | D1: Induced (build) | E1: Build total | F1: Permanent (operating) | G1: All jobs supported | H1: Labour force (m) | I1: Fall in open unemployment (pp) | J1: Open unemployment rate
A2: 2027 | B2: =SUMPRODUCT((Projects!$D$2:$D$36<=2027)*(Projects!$E$2:$E$36>=2027)*Projects!$J$2:$J$36/(Projects!$E$2:$E$36-Projects!$D$2:$D$36+1)) -> 329467.17 | C2: =SUMPRODUCT((Projects!$D$2:$D$36<=2027)*(Projects!$E$2:$E$36>=2027)*Projects!$K$2:$K$36/(Projects!$E$2:$E$36-Projects!$D$2:$D$36+1)) -> 318507.87 | D2: =SUMPRODUCT((Projects!$D$2:$D$36<=2027)*(Projects!$E$2:$E$36>=2027)*Projects!$L$2:$L$36/(Projects!$E$2:$E$36-Projects!$D$2:$D$36+1)) -> 226791.27 | E2: =B2+C2+D2 -> 874766.31 | F2: =SUMPRODUCT((Projects!$E$2:$E$36<2027)*Projects!$R$2:$R$36) -> 0 | G2: =E2+F2 -> 874766.31 | H2: =Assumptions!$C$24*(1+Assumptions!$C$27)^(2027-2026) -> 156.7999 | I2: =G2/1000000*Assumptions!$C$28/H2*100 -> 0.22315481 | J2: =Assumptions!$C$26-I2/100 -> 0.044505267
A3: 2028 | B3: =SUMPRODUCT((Projects!$D$2:$D$36<=2028)*(Projects!$E$2:$E$36>=2028)*Projects!$J$2:$J$36/(Projects!$E$2:$E$36-Projects!$D$2:$D$36+1)) -> 987034.11 | C3: =SUMPRODUCT((Projects!$D$2:$D$36<=2028)*(Projects!$E$2:$E$36>=2028)*Projects!$K$2:$K$36/(Projects!$E$2:$E$36-Projects!$D$2:$D$36+1)) -> 911586.19 | D3: =SUMPRODUCT((Projects!$D$2:$D$36<=2028)*(Projects!$E$2:$E$36>=2028)*Projects!$L$2:$L$36/(Projects!$E$2:$E$36-Projects!$D$2:$D$36+1)) -> 664517.1 | E3: =B3+C3+D3 -> 2563137.4 | F3: =SUMPRODUCT((Projects!$E$2:$E$36<2028)*Projects!$R$2:$R$36) -> 0 | G3: =E3+F3 -> 2563137.4 | H3: =Assumptions!$C$24*(1+Assumptions!$C$27)^(2028-2026) -> 158.71286 | I3: =G3/1000000*Assumptions!$C$28/H3*100 -> 0.64598102 | J3: =Assumptions!$C$26-I3/100 -> 0.040277005
A4: 2029 | B4: =SUMPRODUCT((Projects!$D$2:$D$36<=2029)*(Projects!$E$2:$E$36>=2029)*Projects!$J$2:$J$36/(Projects!$E$2:$E$36-Projects!$D$2:$D$36+1)) -> 1015607.9 | C4: =SUMPRODUCT((Projects!$D$2:$D$36<=2029)*(Projects!$E$2:$E$36>=2029)*Projects!$K$2:$K$36/(Projects!$E$2:$E$36-Projects!$D$2:$D$36+1)) -> 954446.86 | D4: =SUMPRODUCT((Projects!$D$2:$D$36<=2029)*(Projects!$E$2:$E$36>=2029)*Projects!$L$2:$L$36/(Projects!$E$2:$E$36-Projects!$D$2:$D$36+1)) -> 689519.16 | E4: =B4+C4+D4 -> 2659573.9 | F4: =SUMPRODUCT((Projects!$E$2:$E$36<2029)*Projects!$R$2:$R$36) -> 0 | G4: =E4+F4 -> 2659573.9 | H4: =Assumptions!$C$24*(1+Assumptions!$C$27)^(2029-2026) -> 160.64916 | I4: =G4/1000000*Assumptions!$C$28/H4*100 -> 0.66220675 | J4: =Assumptions!$C$26-I4/100 -> 0.040114747
A5: 2030 | B5: =SUMPRODUCT((Projects!$D$2:$D$36<=2030)*(Projects!$E$2:$E$36>=2030)*Projects!$J$2:$J$36/(Projects!$E$2:$E$36-Projects!$D$2:$D$36+1)) -> 999611.4 | C5: =SUMPRODUCT((Projects!$D$2:$D$36<=2030)*(Projects!$E$2:$E$36>=2030)*Projects!$K$2:$K$36/(Projects!$E$2:$E$36-Projects!$D$2:$D$36+1)) -> 934895.59 | D5: =SUMPRODUCT((Projects!$D$2:$D$36<=2030)*(Projects!$E$2:$E$36>=2030)*Projects!$L$2:$L$36/(Projects!$E$2:$E$36-Projects!$D$2:$D$36+1)) -> 677077.44 | E5: =B5+C5+D5 -> 2611584.4 | F5: =SUMPRODUCT((Projects!$E$2:$E$36<2030)*Projects!$R$2:$R$36) -> 24300 | G5: =E5+F5 -> 2635884.4 | H5: =Assumptions!$C$24*(1+Assumptions!$C$27)^(2030-2026) -> 162.60908 | I5: =G5/1000000*Assumptions!$C$28/H5*100 -> 0.64839786 | J5: =Assumptions!$C$26-I5/100 -> 0.040252836
A6: 2031 | B6: =SUMPRODUCT((Projects!$D$2:$D$36<=2031)*(Projects!$E$2:$E$36>=2031)*Projects!$J$2:$J$36/(Projects!$E$2:$E$36-Projects!$D$2:$D$36+1)) -> 895195.27 | C6: =SUMPRODUCT((Projects!$D$2:$D$36<=2031)*(Projects!$E$2:$E$36>=2031)*Projects!$K$2:$K$36/(Projects!$E$2:$E$36-Projects!$D$2:$D$36+1)) -> 802948.66 | D6: =SUMPRODUCT((Projects!$D$2:$D$36<=2031)*(Projects!$E$2:$E$36>=2031)*Projects!$L$2:$L$36/(Projects!$E$2:$E$36-Projects!$D$2:$D$36+1)) -> 594350.38 | E6: =B6+C6+D6 -> 2292494.3 | F6: =SUMPRODUCT((Projects!$E$2:$E$36<2031)*Projects!$R$2:$R$36) -> 92468.304 | G6: =E6+F6 -> 2384962.6 | H6: =Assumptions!$C$24*(1+Assumptions!$C$27)^(2031-2026) -> 164.59291 | I6: =G6/1000000*Assumptions!$C$28/H6*100 -> 0.57960277 | J6: =Assumptions!$C$26-I6/100 -> 0.040940787
A7: 2032 | B7: =SUMPRODUCT((Projects!$D$2:$D$36<=2032)*(Projects!$E$2:$E$36>=2032)*Projects!$J$2:$J$36/(Projects!$E$2:$E$36-Projects!$D$2:$D$36+1)) -> 155505.26 | C7: =SUMPRODUCT((Projects!$D$2:$D$36<=2032)*(Projects!$E$2:$E$36>=2032)*Projects!$K$2:$K$36/(Projects!$E$2:$E$36-Projects!$D$2:$D$36+1)) -> 148515.5 | D7: =SUMPRODUCT((Projects!$D$2:$D$36<=2032)*(Projects!$E$2:$E$36>=2032)*Projects!$L$2:$L$36/(Projects!$E$2:$E$36-Projects!$D$2:$D$36+1)) -> 106407.26 | E7: =B7+C7+D7 -> 410428.02 | F7: =SUMPRODUCT((Projects!$E$2:$E$36<2032)*Projects!$R$2:$R$36) -> 883655.7 | G7: =E7+F7 -> 1294083.7 | H7: =Assumptions!$C$24*(1+Assumptions!$C$27)^(2032-2026) -> 166.60094 | I7: =G7/1000000*Assumptions!$C$28/H7*100 -> 0.31070262 | J7: =Assumptions!$C$26-I7/100 -> 0.043629789
A8: 2033 | B8: =SUMPRODUCT((Projects!$D$2:$D$36<=2033)*(Projects!$E$2:$E$36>=2033)*Projects!$J$2:$J$36/(Projects!$E$2:$E$36-Projects!$D$2:$D$36+1)) -> 0 | C8: =SUMPRODUCT((Projects!$D$2:$D$36<=2033)*(Projects!$E$2:$E$36>=2033)*Projects!$K$2:$K$36/(Projects!$E$2:$E$36-Projects!$D$2:$D$36+1)) -> 0 | D8: =SUMPRODUCT((Projects!$D$2:$D$36<=2033)*(Projects!$E$2:$E$36>=2033)*Projects!$L$2:$L$36/(Projects!$E$2:$E$36-Projects!$D$2:$D$36+1)) -> 0 | E8: =B8+C8+D8 -> 0 | F8: =SUMPRODUCT((Projects!$E$2:$E$36<2033)*Projects!$R$2:$R$36) -> 976197.02 | G8: =E8+F8 -> 976197.02 | H8: =Assumptions!$C$24*(1+Assumptions!$C$27)^(2033-2026) -> 168.63347 | I8: =G8/1000000*Assumptions!$C$28/H8*100 -> 0.23155475 | J8: =Assumptions!$C$26-I8/100 -> 0.044421267
A9: 2034 | B9: =SUMPRODUCT((Projects!$D$2:$D$36<=2034)*(Projects!$E$2:$E$36>=2034)*Projects!$J$2:$J$36/(Projects!$E$2:$E$36-Projects!$D$2:$D$36+1)) -> 0 | C9: =SUMPRODUCT((Projects!$D$2:$D$36<=2034)*(Projects!$E$2:$E$36>=2034)*Projects!$K$2:$K$36/(Projects!$E$2:$E$36-Projects!$D$2:$D$36+1)) -> 0 | D9: =SUMPRODUCT((Projects!$D$2:$D$36<=2034)*(Projects!$E$2:$E$36>=2034)*Projects!$L$2:$L$36/(Projects!$E$2:$E$36-Projects!$D$2:$D$36+1)) -> 0 | E9: =B9+C9+D9 -> 0 | F9: =SUMPRODUCT((Projects!$E$2:$E$36<2034)*Projects!$R$2:$R$36) -> 976197.02 | G9: =E9+F9 -> 976197.02 | H9: =Assumptions!$C$24*(1+Assumptions!$C$27)^(2034-2026) -> 170.6908 | I9: =G9/1000000*Assumptions!$C$28/H9*100 -> 0.22876383 | J9: =Assumptions!$C$26-I9/100 -> 0.044449177
A10: 2035 | B10: =SUMPRODUCT((Projects!$D$2:$D$36<=2035)*(Projects!$E$2:$E$36>=2035)*Projects!$J$2:$J$36/(Projects!$E$2:$E$36-Projects!$D$2:$D$36+1)) -> 0 | C10: =SUMPRODUCT((Projects!$D$2:$D$36<=2035)*(Projects!$E$2:$E$36>=2035)*Projects!$K$2:$K$36/(Projects!$E$2:$E$36-Projects!$D$2:$D$36+1)) -> 0 | D10: =SUMPRODUCT((Projects!$D$2:$D$36<=2035)*(Projects!$E$2:$E$36>=2035)*Projects!$L$2:$L$36/(Projects!$E$2:$E$36-Projects!$D$2:$D$36+1)) -> 0 | E10: =B10+C10+D10 -> 0 | F10: =SUMPRODUCT((Projects!$E$2:$E$36<2035)*Projects!$R$2:$R$36) -> 976197.02 | G10: =E10+F10 -> 976197.02 | H10: =Assumptions!$C$24*(1+Assumptions!$C$27)^(2035-2026) -> 172.77323 | I10: =G10/1000000*Assumptions!$C$28/H10*100 -> 0.22600655 | J10: =Assumptions!$C$26-I10/100 -> 0.044476749
A11: 2036 | B11: =SUMPRODUCT((Projects!$D$2:$D$36<=2036)*(Projects!$E$2:$E$36>=2036)*Projects!$J$2:$J$36/(Projects!$E$2:$E$36-Projects!$D$2:$D$36+1)) -> 0 | C11: =SUMPRODUCT((Projects!$D$2:$D$36<=2036)*(Projects!$E$2:$E$36>=2036)*Projects!$K$2:$K$36/(Projects!$E$2:$E$36-Projects!$D$2:$D$36+1)) -> 0 | D11: =SUMPRODUCT((Projects!$D$2:$D$36<=2036)*(Projects!$E$2:$E$36>=2036)*Projects!$L$2:$L$36/(Projects!$E$2:$E$36-Projects!$D$2:$D$36+1)) -> 0 | E11: =B11+C11+D11 -> 0 | F11: =SUMPRODUCT((Projects!$E$2:$E$36<2036)*Projects!$R$2:$R$36) -> 976197.02 | G11: =E11+F11 -> 976197.02 | H11: =Assumptions!$C$24*(1+Assumptions!$C$27)^(2036-2026) -> 174.88106 | I11: =G11/1000000*Assumptions!$C$28/H11*100 -> 0.2232825 | J11: =Assumptions!$C$26-I11/100 -> 0.04450399
A12: 2037 | B12: =SUMPRODUCT((Projects!$D$2:$D$36<=2037)*(Projects!$E$2:$E$36>=2037)*Projects!$J$2:$J$36/(Projects!$E$2:$E$36-Projects!$D$2:$D$36+1)) -> 0 | C12: =SUMPRODUCT((Projects!$D$2:$D$36<=2037)*(Projects!$E$2:$E$36>=2037)*Projects!$K$2:$K$36/(Projects!$E$2:$E$36-Projects!$D$2:$D$36+1)) -> 0 | D12: =SUMPRODUCT((Projects!$D$2:$D$36<=2037)*(Projects!$E$2:$E$36>=2037)*Projects!$L$2:$L$36/(Projects!$E$2:$E$36-Projects!$D$2:$D$36+1)) -> 0 | E12: =B12+C12+D12 -> 0 | F12: =SUMPRODUCT((Projects!$E$2:$E$36<2037)*Projects!$R$2:$R$36) -> 976197.02 | G12: =E12+F12 -> 976197.02 | H12: =Assumptions!$C$24*(1+Assumptions!$C$27)^(2037-2026) -> 177.01461 | I12: =G12/1000000*Assumptions!$C$28/H12*100 -> 0.22059129 | J12: =Assumptions!$C$26-I12/100 -> 0.044530902
A13: 2038 | B13: =SUMPRODUCT((Projects!$D$2:$D$36<=2038)*(Projects!$E$2:$E$36>=2038)*Projects!$J$2:$J$36/(Projects!$E$2:$E$36-Projects!$D$2:$D$36+1)) -> 0 | C13: =SUMPRODUCT((Projects!$D$2:$D$36<=2038)*(Projects!$E$2:$E$36>=2038)*Projects!$K$2:$K$36/(Projects!$E$2:$E$36-Projects!$D$2:$D$36+1)) -> 0 | D13: =SUMPRODUCT((Projects!$D$2:$D$36<=2038)*(Projects!$E$2:$E$36>=2038)*Projects!$L$2:$L$36/(Projects!$E$2:$E$36-Projects!$D$2:$D$36+1)) -> 0 | E13: =B13+C13+D13 -> 0 | F13: =SUMPRODUCT((Projects!$E$2:$E$36<2038)*Projects!$R$2:$R$36) -> 976197.02 | G13: =E13+F13 -> 976197.02 | H13: =Assumptions!$C$24*(1+Assumptions!$C$27)^(2038-2026) -> 179.17419 | I13: =G13/1000000*Assumptions!$C$28/H13*100 -> 0.21793251 | J13: =Assumptions!$C$26-I13/100 -> 0.04455749
A14: 2039 | B14: =SUMPRODUCT((Projects!$D$2:$D$36<=2039)*(Projects!$E$2:$E$36>=2039)*Projects!$J$2:$J$36/(Projects!$E$2:$E$36-Projects!$D$2:$D$36+1)) -> 0 | C14: =SUMPRODUCT((Projects!$D$2:$D$36<=2039)*(Projects!$E$2:$E$36>=2039)*Projects!$K$2:$K$36/(Projects!$E$2:$E$36-Projects!$D$2:$D$36+1)) -> 0 | D14: =SUMPRODUCT((Projects!$D$2:$D$36<=2039)*(Projects!$E$2:$E$36>=2039)*Projects!$L$2:$L$36/(Projects!$E$2:$E$36-Projects!$D$2:$D$36+1)) -> 0 | E14: =B14+C14+D14 -> 0 | F14: =SUMPRODUCT((Projects!$E$2:$E$36<2039)*Projects!$R$2:$R$36) -> 976197.02 | G14: =E14+F14 -> 976197.02 | H14: =Assumptions!$C$24*(1+Assumptions!$C$27)^(2039-2026) -> 181.36012 | I14: =G14/1000000*Assumptions!$C$28/H14*100 -> 0.21530578 | J14: =Assumptions!$C$26-I14/100 -> 0.044583757
A15: 2040 | B15: =SUMPRODUCT((Projects!$D$2:$D$36<=2040)*(Projects!$E$2:$E$36>=2040)*Projects!$J$2:$J$36/(Projects!$E$2:$E$36-Projects!$D$2:$D$36+1)) -> 0 | C15: =SUMPRODUCT((Projects!$D$2:$D$36<=2040)*(Projects!$E$2:$E$36>=2040)*Projects!$K$2:$K$36/(Projects!$E$2:$E$36-Projects!$D$2:$D$36+1)) -> 0 | D15: =SUMPRODUCT((Projects!$D$2:$D$36<=2040)*(Projects!$E$2:$E$36>=2040)*Projects!$L$2:$L$36/(Projects!$E$2:$E$36-Projects!$D$2:$D$36+1)) -> 0 | E15: =B15+C15+D15 -> 0 | F15: =SUMPRODUCT((Projects!$E$2:$E$36<2040)*Projects!$R$2:$R$36) -> 976197.02 | G15: =E15+F15 -> 976197.02 | H15: =Assumptions!$C$24*(1+Assumptions!$C$27)^(2040-2026) -> 183.57271 | I15: =G15/1000000*Assumptions!$C$28/H15*100 -> 0.21271071 | J15: =Assumptions!$C$26-I15/100 -> 0.044609708
A17: Gross jobs supported, not net of displacement. The fall in open unemployment applies the pass-through share in Assumptions; it compares with a baseline where the rate stays at its Feb 2026 level.

Sheet By cluster
A1: Cluster | B1: Investment (Rp T) | C1: Direct job-years | D1: Indirect job-years | E1: Induced job-years | F1: Total job-years (build) | G1: Job-years per Rp 1 T | H1: Permanent direct jobs | I1: Permanent jobs (total)
A2: Natural resources | B2: =SUMIFS(Projects!$C$2:$C$36,Projects!$B$2:$B$36,"NR") -> 647.847 | C2: =SUMIFS(Projects!$J$2:$J$36,Projects!$B$2:$B$36,"NR") -> 1005590.1 | D2: =SUMIFS(Projects!$K$2:$K$36,Projects!$B$2:$B$36,"NR") -> 1225214.9 | E2: =SUMIFS(Projects!$L$2:$L$36,Projects!$B$2:$B$36,"NR") -> 780781.73 | F2: =SUMIFS(Projects!$M$2:$M$36,Projects!$B$2:$B$36,"NR") -> 3011586.7 | G2: =F2/B2 -> 4648.6079 | H2: =SUMIFS(Projects!$P$2:$P$36,Projects!$B$2:$B$36,"NR") -> 141602.06 | I2: =SUMIFS(Projects!$R$2:$R$36,Projects!$B$2:$B$36,"NR") -> 344093.01
A3: Infrastructure | B3: =SUMIFS(Projects!$C$2:$C$36,Projects!$B$2:$B$36,"INF") -> 1112.623 | C3: =SUMIFS(Projects!$J$2:$J$36,Projects!$B$2:$B$36,"INF") -> 2906197.2 | D3: =SUMIFS(Projects!$K$2:$K$36,Projects!$B$2:$B$36,"INF") -> 2265501.8 | E3: =SUMIFS(Projects!$L$2:$L$36,Projects!$B$2:$B$36,"INF") -> 1810094.6 | F3: =SUMIFS(Projects!$M$2:$M$36,Projects!$B$2:$B$36,"INF") -> 6981793.6 | G3: =F3/B3 -> 6275.0757 | H3: =SUMIFS(Projects!$P$2:$P$36,Projects!$B$2:$B$36,"INF") -> 121661.56 | I3: =SUMIFS(Projects!$R$2:$R$36,Projects!$B$2:$B$36,"INF") -> 295637.59
A4: Defence | B4: =SUMIFS(Projects!$C$2:$C$36,Projects!$B$2:$B$36,"DEF") -> 224.985 | C4: =SUMIFS(Projects!$J$2:$J$36,Projects!$B$2:$B$36,"DEF") -> 271953.03 | D4: =SUMIFS(Projects!$K$2:$K$36,Projects!$B$2:$B$36,"DEF") -> 334364.78 | E4: =SUMIFS(Projects!$L$2:$L$36,Projects!$B$2:$B$36,"DEF") -> 212211.24 | F4: =SUMIFS(Projects!$M$2:$M$36,Projects!$B$2:$B$36,"DEF") -> 818529.05 | G4: =F4/B4 -> 3638.1494 | H4: =SUMIFS(Projects!$P$2:$P$36,Projects!$B$2:$B$36,"DEF") -> 27547.55 | I4: =SUMIFS(Projects!$R$2:$R$36,Projects!$B$2:$B$36,"DEF") -> 66940.546
A5: Others | B5: =SUMIFS(Projects!$C$2:$C$36,Projects!$B$2:$B$36,"OTH") -> 106.02 | C5: =SUMIFS(Projects!$J$2:$J$36,Projects!$B$2:$B$36,"OTH") -> 198680.77 | D5: =SUMIFS(Projects!$K$2:$K$36,Projects!$B$2:$B$36,"OTH") -> 245819.27 | E5: =SUMIFS(Projects!$L$2:$L$36,Projects!$B$2:$B$36,"OTH") -> 155575.01 | F5: =SUMIFS(Projects!$M$2:$M$36,Projects!$B$2:$B$36,"OTH") -> 600075.05 | G5: =F5/B5 -> 5660.0175 | H5: =SUMIFS(Projects!$P$2:$P$36,Projects!$B$2:$B$36,"OTH") -> 110916 | I5: =SUMIFS(Projects!$R$2:$R$36,Projects!$B$2:$B$36,"OTH") -> 269525.88
A6: Total | B6: =SUM(B2:B5) -> 2091.475 | C6: =SUM(C2:C5) -> 4382421.1 | D6: =SUM(D2:D5) -> 4070900.7 | E6: =SUM(E2:E5) -> 2958662.6 | F6: =SUM(F2:F5) -> 11411984 | G6: =F6/B6 -> 5456.4288 | H6: =SUM(H2:H5) -> 401727.17 | I6: =SUM(I2:I5) -> 976197.02
